CongLingdaoYiGoujianJiyuFabricSdkGoDeWebYingyong/README.md
CongLingdaoYiGoujianJiyuFabricSdkGoDeWebYingyong/__init__.py
CongLingdaoYiGoujianJiyuFabricSdkGoDeWebYingyong/__main__.py
CongLingdaoYiGoujianJiyuFabricSdkGoDeWebYingyong/file.epub
CongLingdaoYiGoujianJiyuFabricSdkGoDeWebYingyong/index.html
CongLingdaoYiGoujianJiyuFabricSdkGoDeWebYingyong/css/__init__.py
CongLingdaoYiGoujianJiyuFabricSdkGoDeWebYingyong/css/annotations.css
CongLingdaoYiGoujianJiyuFabricSdkGoDeWebYingyong/css/main.css
CongLingdaoYiGoujianJiyuFabricSdkGoDeWebYingyong/css/normalize.css
CongLingdaoYiGoujianJiyuFabricSdkGoDeWebYingyong/css/popup.css
CongLingdaoYiGoujianJiyuFabricSdkGoDeWebYingyong/font/__init__.py
CongLingdaoYiGoujianJiyuFabricSdkGoDeWebYingyong/font/fontello.eot
CongLingdaoYiGoujianJiyuFabricSdkGoDeWebYingyong/font/fontello.svg
CongLingdaoYiGoujianJiyuFabricSdkGoDeWebYingyong/font/fontello.ttf
CongLingdaoYiGoujianJiyuFabricSdkGoDeWebYingyong/font/fontello.woff
CongLingdaoYiGoujianJiyuFabricSdkGoDeWebYingyong/img/__init__.py
CongLingdaoYiGoujianJiyuFabricSdkGoDeWebYingyong/img/annotator-glyph-sprite.png
CongLingdaoYiGoujianJiyuFabricSdkGoDeWebYingyong/img/annotator-icon-sprite.png
CongLingdaoYiGoujianJiyuFabricSdkGoDeWebYingyong/img/apple-touch-icon.png
CongLingdaoYiGoujianJiyuFabricSdkGoDeWebYingyong/img/cancelfullscreen.png
CongLingdaoYiGoujianJiyuFabricSdkGoDeWebYingyong/img/close.png
CongLingdaoYiGoujianJiyuFabricSdkGoDeWebYingyong/img/fullscreen.png
CongLingdaoYiGoujianJiyuFabricSdkGoDeWebYingyong/img/loader.gif
CongLingdaoYiGoujianJiyuFabricSdkGoDeWebYingyong/img/menu-icon.png
CongLingdaoYiGoujianJiyuFabricSdkGoDeWebYingyong/img/save.png
CongLingdaoYiGoujianJiyuFabricSdkGoDeWebYingyong/img/saved.png
CongLingdaoYiGoujianJiyuFabricSdkGoDeWebYingyong/img/settings-s.png
CongLingdaoYiGoujianJiyuFabricSdkGoDeWebYingyong/img/settings.png
CongLingdaoYiGoujianJiyuFabricSdkGoDeWebYingyong/img/star.png
CongLingdaoYiGoujianJiyuFabricSdkGoDeWebYingyong/js/__init__.py
cong_lingdao_yi_goujian_jiyu_fabric_sdk_go_de_web_yingyong-2024.3.5.0.dist-info/METADATA
cong_lingdao_yi_goujian_jiyu_fabric_sdk_go_de_web_yingyong-2024.3.5.0.dist-info/WHEEL
cong_lingdao_yi_goujian_jiyu_fabric_sdk_go_de_web_yingyong-2024.3.5.0.dist-info/entry_points.txt
cong_lingdao_yi_goujian_jiyu_fabric_sdk_go_de_web_yingyong-2024.3.5.0.dist-info/top_level.txt
cong_lingdao_yi_goujian_jiyu_fabric_sdk_go_de_web_yingyong-2024.3.5.0.dist-info/RECORD
